agora_cli/__init__.py
agora_cli/add.py
agora_cli/compute.py
agora_cli/delete.py
agora_cli/discover.py
agora_cli/export.py
agora_cli/get.py
agora_cli/init.py
agora_cli/learn.py
agora_cli/list.py
agora_cli/metadata.json
agora_cli/publish.py
agora_cli/qgl.py
agora_cli/query.py
agora_cli/root.py
agora_cli/show.py
agora_cli/utils.py
agora_cli-0.0.24.dist-info/LICENSE
agora_cli-0.0.24.dist-info/METADATA
agora_cli-0.0.24.dist-info/WHEEL
agora_cli-0.0.24.dist-info/entry_points.txt
agora_cli-0.0.24.dist-info/top_level.txt
agora_cli-0.0.24.dist-info/RECORD
